file_hub_client/__init__.py
file_hub_client/client.py
file_hub_client/py.typed
file_hub_client/enums/__init__.py
file_hub_client/enums/export_format.py
file_hub_client/enums/role.py
file_hub_client/enums/upload_mode.py
file_hub_client/errors/__init__.py
file_hub_client/errors/exceptions.py
file_hub_client/rpc/__init__.py
file_hub_client/rpc/async_client.py
file_hub_client/rpc/generate_grpc.py
file_hub_client/rpc/interceptors.py
file_hub_client/rpc/sync_client.py
file_hub_client/rpc/gen/__init__.py
file_hub_client/rpc/gen/file_service_pb2.py
file_hub_client/rpc/gen/file_service_pb2_grpc.py
file_hub_client/rpc/gen/folder_service_pb2.py
file_hub_client/rpc/gen/folder_service_pb2_grpc.py
file_hub_client/rpc/gen/taple_service_pb2.py
file_hub_client/rpc/gen/taple_service_pb2_grpc.py
file_hub_client/rpc/protos/file_service.proto
file_hub_client/rpc/protos/folder_service.proto
file_hub_client/rpc/protos/taple_service.proto
file_hub_client/schemas/__init__.py
file_hub_client/schemas/context.py
file_hub_client/schemas/file.py
file_hub_client/schemas/folder.py
file_hub_client/schemas/taple.py
file_hub_client/services/__init__.py
file_hub_client/services/file/__init__.py
file_hub_client/services/file/async_blob_service.py
file_hub_client/services/file/async_file_service.py
file_hub_client/services/file/base_file_service.py
file_hub_client/services/file/sync_blob_service.py
file_hub_client/services/file/sync_file_service.py
file_hub_client/services/folder/__init__.py
file_hub_client/services/folder/async_folder_service.py
file_hub_client/services/folder/sync_folder_service.py
file_hub_client/services/taple/__init__.py
file_hub_client/services/taple/async_taple_service.py
file_hub_client/services/taple/base_taple_service.py
file_hub_client/services/taple/idempotent_taple_mixin.py
file_hub_client/services/taple/sync_taple_service.py
file_hub_client/utils/__init__.py
file_hub_client/utils/converter.py
file_hub_client/utils/download_helper.py
file_hub_client/utils/file_utils.py
tamar_file_hub_client-0.2.7.dist-info/METADATA
tamar_file_hub_client-0.2.7.dist-info/WHEEL
tamar_file_hub_client-0.2.7.dist-info/top_level.txt
tamar_file_hub_client-0.2.7.dist-info/RECORD
