Metadata-Version: 2.4
Name: tamar-file-hub-client
Version: 0.2.7
Summary: A Python SDK for gRPC-based file management system
Home-page: https://github.com/Tamar-Edge-AI/file-hub-client
Author: Oscar Ou
Author-email: oscar.ou@tamaredge.ai
License: MIT
Classifier: Development Status :: 4 - Beta
Classifier: Intended Audience :: Developers
Classifier: License :: OSI Approved :: MIT License
Classifier: Operating System :: OS Independent
Classifier: Programming Language :: Python :: 3
Classifier: Programming Language :: Python :: 3.8
Classifier: Programming Language :: Python :: 3.9
Classifier: Programming Language :: Python :: 3.10
Classifier: Programming Language :: Python :: 3.11
Classifier: Programming Language :: Python :: 3.12
Classifier: Topic :: Software Development :: Libraries :: Python Modules
Classifier: Topic :: Internet :: WWW/HTTP
Classifier: Topic :: Communications :: File Sharing
Classifier: Framework :: AsyncIO
Classifier: Typing :: Typed
Requires-Python: >=3.8
Requires-Dist: grpcio>=1.67.1
Requires-Dist: grpcio-tools>=1.67.1
Requires-Dist: protobuf>=5.29.4
Requires-Dist: pydantic>=2.0.0
Requires-Dist: typing-extensions>=4.0.0; python_version < "3.10"
Requires-Dist: requests>=2.28.0
Requires-Dist: aiohttp>=3.8.0
Requires-Dist: aiofiles>=23.0.0
Requires-Dist: python-magic; platform_system != "Windows"
Requires-Dist: python-magic-bin~=0.4.14; platform_system == "Windows"
Dynamic: author
Dynamic: author-email
Dynamic: classifier
Dynamic: description
Dynamic: description-content-type
Dynamic: home-page
Dynamic: license
Dynamic: requires-dist
Dynamic: requires-python
Dynamic: summary
